lipyphilic-0.12.1.dist-info/METADATA
lipyphilic-0.12.1.dist-info/WHEEL
lipyphilic-0.12.1.dist-info/licenses/AUTHORS.rst
lipyphilic-0.12.1.dist-info/licenses/LICENSE
lipyphilic/__init__.py
lipyphilic/_lipyferric.cpython-313-powerpc64le-linux-gnu.so
lipyphilic/_simple_systems/__init__
lipyphilic/_simple_systems/pdbs/Chol-Flip-Flop.pdb
lipyphilic/_simple_systems/pdbs/HexGrid-2AtomsPerLipid-OverlappingAtoms.pdb
lipyphilic/_simple_systems/pdbs/HexGrid-2AtomsPerLipid-SplitAcrossZ.pdb
lipyphilic/_simple_systems/pdbs/HexGrid-2AtomsPerLipid-TranslatedIn_y.pdb
lipyphilic/_simple_systems/pdbs/HexGrid-2AtomsPerLipid-Undulating-Midplane-Atom.pdb
lipyphilic/_simple_systems/pdbs/HexGrid-2AtomsPerLipid-Undulating-Midplane-Molecule.pdb
lipyphilic/_simple_systems/pdbs/HexGrid-2AtomsPerLipid-Undulating.pdb
lipyphilic/_simple_systems/pdbs/HexGrid-2AtomsPerLipid.pdb
lipyphilic/_simple_systems/pdbs/HexGrid-4AtomsPerLipid-Monolayer.pdb
lipyphilic/_simple_systems/pdbs/Triclinic-3Atoms.pdb
lipyphilic/_simple_systems/simple_systems.py
lipyphilic/_simple_systems/xtcs/.Chol-Flip-Flop.xtc_offsets.npz
lipyphilic/_simple_systems/xtcs/.HexGrid-2AtomsPerLipid-TranslatedIn_y.xtc_offsets.npz
lipyphilic/_simple_systems/xtcs/Chol-Flip-Flop.xtc
lipyphilic/_simple_systems/xtcs/HexGrid-2AtomsPerLipid-TranslatedIn_y-GROMACS-nojump.xtc
lipyphilic/_simple_systems/xtcs/HexGrid-2AtomsPerLipid-TranslatedIn_y.xtc
lipyphilic/analysis/__init__.py
lipyphilic/analysis/area_per_lipid.py
lipyphilic/analysis/flip_flop.py
lipyphilic/analysis/lateral_diffusion.py
lipyphilic/analysis/memb_thickness.py
lipyphilic/analysis/neighbours.py
lipyphilic/analysis/order_parameter.py
lipyphilic/analysis/registration.py
lipyphilic/analysis/z_angles.py
lipyphilic/analysis/z_positions.py
lipyphilic/analysis/z_thickness.py
lipyphilic/leaflets/__init__.py
lipyphilic/leaflets/assign_leaflets.py
lipyphilic/lib/area_per_lipid.py
lipyphilic/lib/assign_leaflets.py
lipyphilic/lib/flip_flop.py
lipyphilic/lib/lateral_diffusion.py
lipyphilic/lib/memb_thickness.py
lipyphilic/lib/neighbours.py
lipyphilic/lib/order_parameter.py
lipyphilic/lib/plotting.py
lipyphilic/lib/registration.py
lipyphilic-0.12.1.dist-info/RECORD
