Metadata-Version: 2.4
Name: lipyphilic
Version: 0.12.1
Classifier: Development Status :: 4 - Beta
Classifier: Intended Audience :: Science/Research
Classifier: License :: OSI Approved :: GNU General Public License v2 (GPLv2)
Classifier: Operating System :: Unix
Classifier: Operating System :: POSIX
Classifier: Operating System :: Microsoft :: Windows
Classifier: Programming Language :: Python
Classifier: Programming Language :: Python :: 3
Classifier: Programming Language :: Python :: 3.11
Classifier: Programming Language :: Python :: 3.12
Classifier: Programming Language :: Rust
Classifier: Topic :: Scientific/Engineering
Requires-Dist: attrs
Requires-Dist: numpy
Requires-Dist: scipy
Requires-Dist: networkx
Requires-Dist: pandas
Requires-Dist: matplotlib
Requires-Dist: mdanalysis
Requires-Dist: freud-analysis
Requires-Dist: tidynamics
Requires-Dist: seaborn
Requires-Dist: tqdm
Requires-Dist: setuptools
Requires-Dist: pytest ; extra == 'tests'
Requires-Dist: pytest-cov ; extra == 'tests'
Requires-Dist: coverage ; extra == 'tests'
Requires-Dist: tox ; extra == 'tests'
Requires-Dist: mdanalysistests ; extra == 'tests'
Requires-Dist: sphinx ; extra == 'docs'
Requires-Dist: sphinx-rtd-theme ; extra == 'docs'
Requires-Dist: maturin>=1.1,<2.0 ; extra == 'docs'
Requires-Dist: lipyphilic[tests,docs] ; extra == 'dev'
Requires-Dist: pre-commit ; extra == 'dev'
Provides-Extra: tests
Provides-Extra: docs
Provides-Extra: dev
License-File: LICENSE
License-File: AUTHORS.rst
Summary: Analyse MD simulations of lipids with python'
Keywords: lipid,molecular dynamics
Author-email: Paul Smith <paul.j.smith@ucl.ac.uk>
Requires-Python: >=3.11
Project-URL: bugtracker, https://github.com/p-j-smith/lipyphilic/issues
Project-URL: documentation, https://lipyphilic.readthedocs.io/en/stable
Project-URL: homepage, https://github.com/p-j-smith/lipyphilic
Project-URL: usersupport, https://github.com/p-j-smith/lipyphilic/discussions
